agent_matrix/__init__.py
agent_matrix/agent_launcher.py
agent_matrix/config.py
agent_matrix/verify_deps.py
agent_matrix/__pycache__/__init__.cpython-310.pyc
agent_matrix/__pycache__/__init__.cpython-312.pyc
agent_matrix/__pycache__/config.cpython-310.pyc
agent_matrix/__pycache__/config.cpython-312.pyc
agent_matrix/agent/__init__.py
agent_matrix/agent/agent.py
agent_matrix/agent/agent_basic_qa.py
agent_matrix/agent/agent_extraction.py
agent_matrix/agent/agent_groupchat_host.py
agent_matrix/agent/agent_proxy.py
agent_matrix/agent/agent_switch.py
agent_matrix/agent/interaction.py
agent_matrix/agent/__pycache__/__init__.cpython-310.pyc
agent_matrix/agent/__pycache__/__init__.cpython-312.pyc
agent_matrix/agent/__pycache__/agent.cpython-310.pyc
agent_matrix/agent/__pycache__/agent.cpython-312.pyc
agent_matrix/agent/__pycache__/agent_basic_qa.cpython-310.pyc
agent_matrix/agent/__pycache__/agent_basic_qa.cpython-312.pyc
agent_matrix/agent/__pycache__/agent_extraction.cpython-310.pyc
agent_matrix/agent/__pycache__/agent_extraction.cpython-312.pyc
agent_matrix/agent/__pycache__/agent_proxy.cpython-310.pyc
agent_matrix/agent/__pycache__/agent_proxy.cpython-312.pyc
agent_matrix/agent/__pycache__/interaction.cpython-310.pyc
agent_matrix/agent/__pycache__/interaction.cpython-312.pyc
agent_matrix/agent/router/agent_multi_downstream.py
agent_matrix/agent/router/__pycache__/agent_multi_downstream.cpython-310.pyc
agent_matrix/agent/router/__pycache__/agent_multi_downstream.cpython-312.pyc
agent_matrix/agent/structure/agent_structured_output.py
agent_matrix/agent/structure/__pycache__/agent_structured_output.cpython-310.pyc
agent_matrix/agent/structure/__pycache__/agent_structured_output.cpython-312.pyc
agent_matrix/agentcraft/agentcraft_fn.py
agent_matrix/agentcraft/agentcraft_proxy.py
agent_matrix/agentcraft/__pycache__/agentcraft_fn.cpython-310.pyc
agent_matrix/agentcraft/__pycache__/agentcraft_fn.cpython-312.pyc
agent_matrix/agentcraft/__pycache__/agentcraft_proxy.cpython-310.pyc
py_agent_matrix-0.1.4.dist-info/METADATA
py_agent_matrix-0.1.4.dist-info/WHEEL
py_agent_matrix-0.1.4.dist-info/top_level.txt
py_agent_matrix-0.1.4.dist-info/RECORD
