Metadata-Version: 2.1
Name: py-agent-matrix
Version: 0.1.4
Summary: Generating high-level intelligent agents via nesting basic LM agents
Home-page: https://github.com/binary-husky/agent-matrix/
Author: Hao Ma, Tianyi Hu, Qingxu Fu
Author-email: qingxu.fu@outlook.com
Project-URL: Bug Tracker, https://github.com/binary-husky/agent-matrix/issues
Classifier: Programming Language :: Python :: 3
Classifier: License :: OSI Approved :: MIT License
Classifier: Operating System :: OS Independent
Requires-Python: >=3.8
Requires-Dist: networkx
Requires-Dist: vhmap
Requires-Dist: loguru
Requires-Dist: cloudpickle
Requires-Dist: void-terminal (>=1.1.2)
